arca_arg/__init__.py
arca_arg/auth.py
arca_arg/settings.py
arca_arg/webservice.py
arca_arg-0.2.2.dist-info/LICENSE
arca_arg-0.2.2.dist-info/METADATA
arca_arg-0.2.2.dist-info/WHEEL
arca_arg-0.2.2.dist-info/top_level.txt
arca_arg-0.2.2.dist-info/RECORD
