Metadata-Version: 2.2
Name: arca_arg
Version: 0.2.2
Summary: API para interactuar con los Web Services de AFIP
Home-page: https://github.com/relopezbriega/arca_arg
Author: Raul E. Lopez Briega
Author-email: relopezbriega@gmail.com
Classifier: Programming Language :: Python :: 3
Classifier: License :: OSI Approved :: MIT License
Classifier: Operating System :: OS Independent
Requires-Python: >=3.8
License-File: LICENSE
Requires-Dist: zeep
Requires-Dist: cryptography
Requires-Dist: python-dateutil
Dynamic: author
Dynamic: author-email
Dynamic: classifier
Dynamic: description
Dynamic: description-content-type
Dynamic: home-page
Dynamic: requires-dist
Dynamic: requires-python
Dynamic: summary
